littlenv/__init__.py
littlenv/littlenv.py
littlenv-0.1.7.dist-info/LICENSE
littlenv-0.1.7.dist-info/METADATA
littlenv-0.1.7.dist-info/WHEEL
littlenv-0.1.7.dist-info/top_level.txt
littlenv-0.1.7.dist-info/RECORD
